{
  "test_id": "schreierorbit_09",
  "oracle_version": "xAct 1.2.0",
  "mathematica_version": "14.3",
  "timestamp": "2026-03-11T20:46:28Z",
  "commands": "a = Cycles[{1, 2, 4, 5, 7, 3, 6}];\nb = Cycles[{2, 4}, {3, 5}];\ns1 = a;\ns2 = b;\ns3 = Cycles[{4, 5}, {6, 7}];\ns4 = Cycles[{4, 6}, {5, 7}];\nB = {1, 2, 4};\nS = GenSet[s1, s2, s3, s4];\nSGS = StrongGenSet[B, S];\ng1 = Perm[{1, 7, 6, 5, 4, 2, 3}];\ng2 = Perm[{1, 2, 3, 7, 6, 5, 4}];\nSchreierOrbit[4, GenSet[s2, s3, s4], 7]\nxAct`xPerm`Schreier[(4, 2, 5, 6, 3, 7), (0, xAct`xPerm`Cycles[(2, 4), (3, 5)], xAct`xPerm`Cycles[(2, 4), (3, 5)], 0, xAct`xPerm`Cycles[(4, 5), (6, 7)], xAct`xPerm`Cycles[(4, 6), (5, 7)], xAct`xPerm`Cycles[(4, 6), (5, 7)]), (0, 4, 5, 0, 4, 4, 5)] === Schreier[{4, 2, 5, 6, 3, 7}, {0, \"s2\", \"s2\", 0, \"s3\", \"s4\", \"s4\"}, {0, 4, 5, 0, 4, 4, 5}]",
  "raw_output": "xAct`xPerm`Schreier[(4, 2, 5, 6, 3, 7), (0, xAct`xPerm`Cycles[(2, 4), (3, 5)], xAct`xPerm`Cycles[(2, 4), (3, 5)], 0, xAct`xPerm`Cycles[(4, 5), (6, 7)], xAct`xPerm`Cycles[(4, 6), (5, 7)], xAct`xPerm`Cycles[(4, 6), (5, 7)]), (0, 4, 5, 0, 4, 4, 5)]",
  "normalized_output": "xAct`xPerm`Schreier[(4, 2, 5, 6, 3, 7), (0, xAct`xPerm`Cycles[(2, 4), (3, 5)], xAct`xPerm`Cycles[(2, 4), (3, 5)], 0, xAct`xPerm`Cycles[(4, 5), (6, 7)], xAct`xPerm`Cycles[(4, 6), (5, 7)], xAct`xPerm`Cycles[(4, 6), (5, 7)]), (0, 4, 5, 0, 4, 4, 5)]",
  "properties": {},
  "hash": "sha256:e35d61fc4ef5"
}
